vggsounder/__init__.py
vggsounder/benchmark.py
vggsounder/labels.py
vggsounder/data/classes.csv
vggsounder/data/vggsounder+background-music.csv
vggsounder/data/vggsounder.csv
vggsounder-0.1.6.dist-info/METADATA
vggsounder-0.1.6.dist-info/WHEEL
vggsounder-0.1.6.dist-info/entry_points.txt
vggsounder-0.1.6.dist-info/licenses/LICENCE
vggsounder-0.1.6.dist-info/RECORD
