Metadata-Version: 2.4
Name: vggsounder
Version: 0.1.6
Summary: A Python package for accessing VGGSounder dataset labels and metadata
Project-URL: Homepage, https://vggsounder.github.io/
Project-URL: Repository, https://github.com/Bizilizi/VGGSounder
Project-URL: Issues, https://github.com/Bizilizi/VGGSounder/issues
Author-email: Daniil Zverev <daniil.zverev@tum.de>
License-File: LICENCE
Keywords: audio,classification,dataset,machine-learning,vgg,video
Classifier: Development Status :: 3 - Alpha
Classifier: Intended Audience :: Developers
Classifier: Intended Audience :: Science/Research
Classifier: License :: OSI Approved :: MIT License
Classifier: Operating System :: OS Independent
Classifier: Programming Language :: Python :: 3
Classifier: Programming Language :: Python :: 3.8
Classifier: Programming Language :: Python :: 3.9
Classifier: Programming Language :: Python :: 3.10
Classifier: Programming Language :: Python :: 3.11
Classifier: Programming Language :: Python :: 3.12
Classifier: Topic :: Multimedia :: Sound/Audio :: Analysis
Classifier: Topic :: Multimedia :: Video :: Display
Classifier: Topic :: Scientific/Engineering :: Artificial Intelligence
Requires-Python: >=3.11
Requires-Dist: datasets>=4.5.0
Provides-Extra: dev
Requires-Dist: crowd-kit>=1.4.1; extra == 'dev'
Requires-Dist: jupyter>=1.1.1; extra == 'dev'
Requires-Dist: matplotlib>=3.10.5; extra == 'dev'
Requires-Dist: numpy>=2.3.2; extra == 'dev'
Requires-Dist: pandas>=2.3.1; extra == 'dev'
Requires-Dist: scikit-learn>=1.7.1; extra == 'dev'
Requires-Dist: tqdm>=4.67.1; extra == 'dev'
